lsprotocol/__init__.py
lsprotocol/_hooks.py
lsprotocol/converters.py
lsprotocol/py.typed
lsprotocol/types.py
lsprotocol/validators.py
lsprotocol-2025.0.0rc1.dist-info/licenses/LICENSE
lsprotocol-2025.0.0rc1.dist-info/WHEEL
lsprotocol-2025.0.0rc1.dist-info/METADATA
lsprotocol-2025.0.0rc1.dist-info/RECORD
