Metadata-Version: 2.4
Name: lsprotocol
Version: 2025.0.0rc1
Summary: Python types for Language Server Protocol.
Author-email: Microsoft Corporation <lsprotocol-help@microsoft.com>
Maintainer-email: Brett Cannon <brett@python.org>, Karthik Nadig <kanadig@microsoft.com>
Requires-Python: >=3.8
Classifier: Development Status :: 4 - Beta
Classifier: License :: OSI Approved :: MIT License
Classifier: Programming Language :: Python
Classifier: Programming Language :: Python :: 3.8
Classifier: Programming Language :: Python :: 3.9
Classifier: Programming Language :: Python :: 3.10
Classifier: Programming Language :: Python :: 3.11
Classifier: Programming Language :: Python :: 3.12
Classifier: Programming Language :: Python :: Implementation :: CPython
Classifier: Programming Language :: Python :: Implementation :: PyPy
License-File: LICENSE
Requires-Dist: attrs>=21.3.0
Requires-Dist: cattrs!=23.2.1
Project-URL: Issues, https://github.com/microsoft/lsprotocol/issues
Project-URL: Source, https://github.com/microsoft/lsprotocol
